[
    {
        "accuracy": 0.467515923566879,
        "batch": 8,
        "best_accuracy": 0.467515923566879,
        "best_epoch": 1,
        "cpu_count": 32,
        "cpu_type": "x86_64",
        "cpu_usage_percent": 6.0,
        "dropout": 0.45018461749163874,
        "duration": 584752549098,
        "epoch_max": 5,
        "gpu_memory_kb": 4422347.0,
        "gpu_memory_usage_percent": 1.28,
        "gpu_total_memory_kb": 24658816.0,
        "gpu_type": "NVIDIA GeForce RTX 4090",
        "gradient_norm": 2.9186014795789292,
        "lr": 0.02501692732601473,
        "momentum": 0.7599746745614896,
        "occupied_gpu_memory_kb": 314794.5,
        "occupied_ram_kb": 5498128.0,
        "ram_usage_percent": 6.8,
        "samples_per_second": 16.19319879450734,
        "test_loss": 1.6028217162231322,
        "total_ram_kb": 131727448.0,
        "train_accuracy": 0.5040658992501849,
        "train_loss": 1.5202607047819607,
        "transform": "bf-v1-RandomHorizontalFlip_RandomAutocontrast_256",
        "uid": "cd94b848e4845fd62d7b40a69560e497"
    },
    {
        "accuracy": 0.40764331210191085,
        "batch": 32,
        "best_accuracy": 0.40764331210191085,
        "best_epoch": 1,
        "cpu_count": 32,
        "cpu_type": "x86_64",
        "cpu_usage_percent": 3.8,
        "dropout": 0.10967521079998821,
        "duration": 192932873986,
        "epoch_max": 5,
        "gpu_memory_kb": 4383435.0,
        "gpu_memory_usage_percent": 1.18,
        "gpu_total_memory_kb": 24658816.0,
        "gpu_type": "NVIDIA GeForce RTX 4090",
        "gradient_norm": 1.009466877764356,
        "lr": 0.2063360547575251,
        "momentum": 0.46057992310604623,
        "occupied_gpu_memory_kb": 291754.5,
        "occupied_ram_kb": 5532140.0,
        "ram_usage_percent": 6.9,
        "samples_per_second": 49.079545361469535,
        "test_loss": 1.77991492670726,
        "total_ram_kb": 131727448.0,
        "train_accuracy": 0.4319357904741789,
        "train_loss": 1.7181560888483718,
        "transform": "norm_128",
        "uid": "3feac344d26d219cd13cc784465296c2"
    },
    {
        "accuracy": 0.4048407643312102,
        "batch": 1,
        "best_accuracy": 0.4048407643312102,
        "best_epoch": 1,
        "dropout": 0.23526179481694798,
        "duration": 351115916222,
        "epoch_max": 5,
        "gpu_memory_kb": 9582563.5,
        "gradient_norm": 3.0000000285120185,
        "lr": 0.006456806320574597,
        "lr_now": 0.006456806320574597,
        "momentum": 0.604832905884926,
        "samples_per_second": 26.968369434803073,
        "test_loss": 1.8021683047064312,
        "train_accuracy": 0.43183018270144685,
        "train_loss": 1.7507635406727207,
        "transform": "bf-v1-Pad_RandomAutocontrast_RandomAdjustSharpnes",
        "uid": "ee143a4088d87f242ede9e8fb99cdcc7"
    },
    {
        "accuracy": 0.3207643312101911,
        "batch": 64,
        "dropout": 0.482142558225371,
        "duration": 43291356920,
        "epoch_max": 1,
        "lr": 0.028035312506170498,
        "momentum": 0.9384931912492857,
        "transform": "bf-v1-RandomRotation_46",
        "uid": "287bddc9b778cb52135d50545b862e34"
    },
    {
        "accuracy": 0.31363057324840765,
        "batch": 256,
        "best_accuracy": 0.31363057324840765,
        "best_epoch": 1,
        "dropout": 0.3244338450589023,
        "duration": 824389739124,
        "epoch_max": 5,
        "gpu_memory_kb": 23272068.0,
        "gradient_norm": 0.8801486747476829,
        "lr": 0.28033900276783774,
        "lr_now": 0.28033900276783774,
        "momentum": 0.9743209138728268,
        "samples_per_second": 11.486087952256558,
        "test_loss": 1.977444313466549,
        "train_accuracy": 0.31946351251452104,
        "train_loss": 1.9524881130940206,
        "transform": "bf-v1-GaussianBlur_57",
        "uid": "c6402ee7b453c887e23f9b37eb93aa45"
    },
    {
        "accuracy": 0.13452229299363058,
        "batch": 16,
        "best_accuracy": 0.13452229299363058,
        "best_epoch": 1,
        "dropout": 0.15708764145049708,
        "duration": 133453109570,
        "epoch_max": 5,
        "gpu_memory_kb": 23271684.0,
        "gradient_norm": 0.21061324055487338,
        "lr": 0.010344404401288646,
        "lr_now": 0.010344404401288646,
        "momentum": 0.07644852690004533,
        "samples_per_second": 70.9542205441401,
        "test_loss": 2.299795411466583,
        "train_accuracy": 0.15513781814341535,
        "train_loss": 2.298855320021913,
        "transform": "bf-v1-RandomAutocontrast_RandomPosterize_5",
        "uid": "37fcd4872f19aae844c2c6dbce67af5c"
    }
]