[
    {
        "accuracy": 0.7868450055104699,
        "batch": 4096,
        "best_accuracy": 0.7868450055104699,
        "best_epoch": 1,
        "cpu_count": 224,
        "cpu_type": "x86_64",
        "cpu_usage_percent": 0.2,
        "dropout": 0.1856511415648049,
        "duration": 469425702697,
        "epoch_max": 1,
        "gpu_memory_kb": 25454367.5,
        "gpu_memory_usage_percent": 0.1,
        "gpu_total_memory_kb": 83025024.0,
        "gpu_type": "NVIDIA H100 80GB HBM3",
        "gradient_norm": 0.6325413566388718,
        "lr": 0.035427318560915674,
        "momentum": 0.6493062277691943,
        "occupied_gpu_memory_kb": 83675.5,
        "occupied_ram_kb": 37983124.0,
        "ram_usage_percent": 2.3,
        "samples_per_second": 346.743225386089,
        "test_loss": 0.4594289541244507,
        "total_ram_kb": 2113462556.0,
        "train_accuracy": 0.7938809362904712,
        "train_loss": 0.45174467489123343,
        "transform": "bf-v1-Pad_RandomAdjustSharpnes_RandomAutocontrast",
        "uid": "fde0d1878b7820d0950a10af3a0f5702"
    }
]