[
    {
        "accuracy": 0.4565605095541401,
        "batch": 64,
        "best_accuracy": 0.4565605095541401,
        "best_epoch": 4,
        "cpu_count": 32,
        "cpu_type": "x86_64",
        "cpu_usage_percent": 8.2,
        "dropout": 0.12940784694956625,
        "duration": 698819912056,
        "epoch_max": 5,
        "gpu_memory_kb": 12712871.5,
        "gpu_memory_usage_percent": 0.1,
        "gpu_total_memory_kb": 24658816.0,
        "gpu_type": "NVIDIA GeForce RTX 4090",
        "gradient_norm": 2.9999998330629385,
        "lr": 0.003058019356196802,
        "momentum": 0.45675471220495756,
        "occupied_gpu_memory_kb": 25707.5,
        "occupied_ram_kb": 5412096.0,
        "ram_usage_percent": 7.2,
        "samples_per_second": 60.13553142377388,
        "test_loss": 1.6710341245897355,
        "total_ram_kb": 131727448.0,
        "train_accuracy": 0.4929770831133171,
        "train_loss": 1.5875870053832595,
        "transform": "bf-v1-RandomSolarize_RandomHorizontalFlip_5",
        "uid": "3bddee46a7468ac805bd86fa6394c8fe"
    },
    {
        "accuracy": 0.37121019108280257,
        "batch": 512,
        "best_accuracy": 0.37121019108280257,
        "best_epoch": 4,
        "cpu_count": 32,
        "cpu_type": "x86_64",
        "cpu_usage_percent": 7.2,
        "dropout": 0.37096262798591123,
        "duration": 851814256467,
        "epoch_max": 5,
        "gpu_memory_kb": 3201887.5,
        "gpu_memory_usage_percent": 0.1,
        "gpu_total_memory_kb": 24658816.0,
        "gpu_type": "NVIDIA GeForce RTX 4090",
        "gradient_norm": 2.999999738261908,
        "lr": 0.0014644552579987896,
        "momentum": 0.39698135215252417,
        "occupied_gpu_memory_kb": 24795.5,
        "occupied_ram_kb": 5284840.0,
        "ram_usage_percent": 7.1,
        "samples_per_second": 44.15034988964547,
        "test_loss": 1.8657328933477402,
        "total_ram_kb": 131727448.0,
        "train_accuracy": 0.3849403316084064,
        "train_loss": 1.838165797685322,
        "transform": "bf-v1-RandomHorizontalFlip_RandomSolarize_RandomAdjustSharpnes",
        "uid": "a1d375287147329f45a68bc66a0092f4"
    },
    {
        "accuracy": 0.3281528662420382,
        "batch": 2048,
        "best_accuracy": 0.3956687898089172,
        "best_epoch": 3,
        "cpu_count": 32,
        "cpu_type": "x86_64",
        "cpu_usage_percent": 0.9,
        "dropout": 0.4452340778727319,
        "duration": 623339613786,
        "epoch_max": 5,
        "gpu_memory_kb": 12712871.5,
        "gpu_memory_usage_percent": 0.1,
        "gpu_total_memory_kb": 24658816.0,
        "gpu_type": "NVIDIA GeForce RTX 4090",
        "gradient_norm": 2.999999333349165,
        "lr": 0.07723907129942084,
        "momentum": 0.18275275400762314,
        "occupied_gpu_memory_kb": 24795.5,
        "occupied_ram_kb": 4506632.0,
        "ram_usage_percent": 6.5,
        "samples_per_second": 82.34892038808032,
        "test_loss": 1.902136504650116,
        "total_ram_kb": 131727448.0,
        "train_accuracy": 0.361284190516422,
        "train_loss": 1.7919328212738037,
        "transform": "bf-v1-RandomSolarize_Pad",
        "uid": "6b15652bbc100509bf24960c6a905a07"
    },
    {
        "accuracy": 0.15694267515923566,
        "batch": 32,
        "best_accuracy": 0.15694267515923566,
        "best_epoch": 4,
        "cpu_count": 32,
        "cpu_type": "x86_64",
        "cpu_usage_percent": 6.2,
        "dropout": 0.05788333881132418,
        "duration": 544559418614,
        "epoch_max": 5,
        "gpu_memory_kb": 12712871.5,
        "gpu_memory_usage_percent": 0.1,
        "gpu_total_memory_kb": 24658816.0,
        "gpu_type": "NVIDIA GeForce RTX 4090",
        "gradient_norm": 2.9999994318403873,
        "lr": 3.196581417238247e-05,
        "momentum": 0.18864996072715845,
        "occupied_gpu_memory_kb": 24795.5,
        "occupied_ram_kb": 5380460.0,
        "ram_usage_percent": 7.2,
        "samples_per_second": 70.96757681734832,
        "test_loss": 2.2532528784216903,
        "total_ram_kb": 131727448.0,
        "train_accuracy": 0.17309113950786778,
        "train_loss": 2.2434225718717316,
        "transform": "bf-v1-CenterCrop_Pad",
        "uid": "1950882a839d192411d2d564764f1635"
    }
]