[
    {
        "accuracy": 0.3638216560509554,
        "batch": 2,
        "best_accuracy": 0.3638216560509554,
        "best_epoch": 4,
        "cpu_count": 32,
        "cpu_type": "x86_64",
        "cpu_usage_percent": 6.3,
        "duration": 903777430655,
        "epoch_max": 5,
        "gpu_memory_kb": 1308887.5,
        "gpu_memory_usage_percent": 0.16,
        "gpu_total_memory_kb": 24658816.0,
        "gpu_type": "NVIDIA GeForce RTX 4090",
        "gradient_norm": 2.9999995895200047,
        "lr": 0.005269769527197325,
        "momentum": 0.23070435567897907,
        "occupied_gpu_memory_kb": 40677.5,
        "occupied_ram_kb": 5431284.0,
        "ram_usage_percent": 6.9,
        "samples_per_second": 35.74152197241001,
        "test_loss": 2.5451680300174324,
        "total_ram_kb": 131727448.0,
        "train_accuracy": 0.38705248706304785,
        "train_loss": 2.494844204880759,
        "transform": "bf-v1-RandomAutocontrast_Pad_4",
        "uid": "b7a6daa1c9537148262f2a69e8e2ddf7"
    }
]